LICENSE
MANIFEST.in
README.md
setup.py
django_auth2/__init__.py
django_auth2/forms.py
django_auth2/mails.py
django_auth2/middleware.py
django_auth2/runtests.py
django_auth2/tasks.py
django_auth2/tokens.py
django_auth2/urls.py
django_auth2/utils.py
django_auth2.egg-info/PKG-INFO
django_auth2.egg-info/SOURCES.txt
django_auth2.egg-info/dependency_links.txt
django_auth2.egg-info/requires.txt
django_auth2.egg-info/top_level.txt
django_auth2/static/django_auth2/css/base.css
django_auth2/templates/django_auth2/base.html
django_auth2/templates/django_auth2/fields_form.html
django_auth2/templates/django_auth2/activate/re_send.html
django_auth2/templates/django_auth2/activate/success.html
django_auth2/templates/django_auth2/login/login.html
django_auth2/templates/django_auth2/mail/send_activation_mail.html
django_auth2/templates/django_auth2/mail/send_reset_password_mail.html
django_auth2/templates/django_auth2/register/email_sended.html
django_auth2/templates/django_auth2/register/register.html
django_auth2/templates/django_auth2/reset_password/complete.html
django_auth2/templates/django_auth2/reset_password/confirm.html
django_auth2/templates/django_auth2/reset_password/done.html
django_auth2/templates/django_auth2/reset_password/email.html
django_auth2/templates/django_auth2/reset_password/form.html
django_auth2/templates/django_auth2/reset_password/subject.txt
django_auth2/tests/__init__.py
django_auth2/tests/base.py
django_auth2/tests/test_login.py
django_auth2/tests/test_register.py
django_auth2/tests/test_settings.py
django_auth2/views/__init__.py
django_auth2/views/activate.py
django_auth2/views/login.py
django_auth2/views/logout.py
django_auth2/views/register.py
django_auth2/views/reset_password.py