Metadata-Version: 1.0
Name: django-auth2
Version: 0.1.1
Summary: Login, Registration, Reset password, ActivateUser
Home-page: https://github.com/Nick1994209/django-auth2/
Author: nick1994209
Author-email: nick1994209@gmail.com
License: MIT
Platform: UNKNOWN
